LICENSE
README.rst
pyproject.toml
requirements.txt
src/mw_plot/MW_2mass.jpg
src/mw_plot/MW_bg_annotate.jpg
src/mw_plot/MW_bg_unannotate.jpg
src/mw_plot/MW_edgeon_edr3_unannotate.jpg
src/mw_plot/MW_farinfrared.jpg
src/mw_plot/MW_fermi_gamma.jpg
src/mw_plot/__init__.py
src/mw_plot/base.py
src/mw_plot/bokeh_backend.py
src/mw_plot/matplotlib_backend.py
src/mw_plot/mplstyle.mplstyle
src/mw_plot/utils.py
src/mw_plot.egg-info/PKG-INFO
src/mw_plot.egg-info/SOURCES.txt
src/mw_plot.egg-info/dependency_links.txt
src/mw_plot.egg-info/requires.txt
src/mw_plot.egg-info/top_level.txt
tests/test_bokeh.py
tests/test_mpl.py