Metadata-Version: 2.1
Name: mw_plot
Version: 0.13.1
Summary: A handy python package to do plotting on a face-on/edge-on/allsky map milkyway with matplotlib and bokeh
Author-email: Henry Leung <henryskyleung@gmail.com>
Maintainer-email: Henry Leung <henryskyleung@gmail.com>
License: Copyright 2018-2024 Henry Leung
Project-URL: Homepage, https://github.com/henrysky/milkyway_plot
Project-URL: Documentation, https://milkyway-plot.readthedocs.io/
Project-URL: Repository, https://github.com/henrysky/milkyway_plot/
Project-URL: Bug Tracker, https://github.com/henrysky/milkyway_plot/issues
Project-URL: Changelog, https://milkyway-plot.readthedocs.io/en/latest/changelog.html
Classifier: Development Status :: 4 - Beta
Classifier: License :: OSI Approved :: MIT License
Classifier: Programming Language :: Python
Classifier: Intended Audience :: Science/Research
Classifier: Topic :: Scientific/Engineering :: Astronomy
Requires-Python: >=3.9
License-File: LICENSE
Requires-Dist: astropy
Requires-Dist: astroquery
Requires-Dist: matplotlib>3.7.0
Requires-Dist: numpy
Requires-Dist: pandas
Requires-Dist: requests
